sparshik/__init__.py
sparshik/kyc/__init__.py
sparshik/kyc/applicants.py
sparshik/kyc/challenge.py
sparshik/kyc/documents.py
sparshik/kyc/mask.py
sparshik/kyc/reports.py
sparshik/kyc/utils.py
sparshik/kyc/version.py
sparshik_kyc-0.2.2.dist-info/LICENSE.md
sparshik_kyc-0.2.2.dist-info/METADATA
sparshik_kyc-0.2.2.dist-info/WHEEL
sparshik_kyc-0.2.2.dist-info/top_level.txt
sparshik_kyc-0.2.2.dist-info/RECORD
