Metadata-Version: 2.1
Name: sparshik-kyc
Version: 0.2.2
Summary: Python SDK for Sparshik KYC API
Home-page: https://github.com/sparshik/kyc-sdk-python
Author: Sparshik Technologies
Author-email: support@sparshik.com
License: MIT License
Platform: UNKNOWN
Classifier: Development Status :: 3 - Alpha
Classifier: Intended Audience :: Developers
Classifier: License :: OSI Approved :: MIT License
Classifier: Programming Language :: Python :: 3
Classifier: Programming Language :: Python :: 3.5
Classifier: Programming Language :: Python :: 3.6
Classifier: Programming Language :: Python :: 3.7
Classifier: Topic :: Scientific/Engineering :: Image Recognition
Classifier: Topic :: Scientific/Engineering :: Artificial Intelligence
Classifier: Operating System :: OS Independent
Requires-Dist: requests
